tiktok_downloader/__init__.py
tiktok_downloader/core.py
tiktok_downloader_hd-0.0a3.dist-info/licenses/LICENSE
tiktok_downloader_hd-0.0a3.dist-info/METADATA
tiktok_downloader_hd-0.0a3.dist-info/WHEEL
tiktok_downloader_hd-0.0a3.dist-info/top_level.txt
tiktok_downloader_hd-0.0a3.dist-info/RECORD
