Metadata-Version: 2.4
Name: tiktok-downloader-hd
Version: 0.0a3
Summary: A Selenium-based HD TikTok video downloader using SnapTik
Home-page: https://github.com/windyx0/tiktok-downloader
Author: Windyx
Author-email: windyxeditor@gmail.com
Classifier: Programming Language :: Python :: 3
Classifier: License :: OSI Approved :: MIT License
Classifier: Operating System :: OS Independent
Requires-Python: >=3.6
License-File: LICENSE
Requires-Dist: selenium
Requires-Dist: yt-dlp
Requires-Dist: requests
Requires-Dist: webdriver-manager
Dynamic: author
Dynamic: author-email
Dynamic: classifier
Dynamic: description
Dynamic: description-content-type
Dynamic: home-page
Dynamic: license-file
Dynamic: requires-dist
Dynamic: requires-python
Dynamic: summary
